{
  "产生性质\\index.md": {
    "id": 1,
    "batch_folder": "0",
    "new_name": "1.md",
    "new_path": "0/1.md",
    "abs_source": "works\\产生性质\\index.md"
  },
  "学术性质\\index.md": {
    "id": 3,
    "batch_folder": "0",
    "new_name": "3.md",
    "new_path": "0/3.md",
    "abs_source": "works\\学术性质\\index.md"
  },
  "普遍性质\\index.md": {
    "id": 2,
    "batch_folder": "0",
    "new_name": "2.md",
    "new_path": "0/2.md",
    "abs_source": "works\\普遍性质\\index.md"
  },
  "产生性质\\物种与身体结构\\身体结构\\身体结构-数量\\index.md": {
    "id": 10,
    "batch_folder": "0",
    "new_name": "10.md",
    "new_path": "0/10.md",
    "abs_source": "works\\产生性质\\物种与身体结构\\身体结构\\身体结构-数量\\index.md"
  },
  "产生性质\\物种与身体结构\\身体结构\\身体结构-数量\\额外口.md": {
    "id": 7,
    "batch_folder": "0",
    "new_name": "7.md",
    "new_path": "0/7.md",
    "abs_source": "works\\产生性质\\物种与身体结构\\身体结构\\身体结构-数量\\额外口.md"
  },
  "产生性质\\物种与身体结构\\身体结构\\身体结构-数量\\额外眼.md": {
    "id": 6,
    "batch_folder": "0",
    "new_name": "6.md",
    "new_path": "0/6.md",
    "abs_source": "works\\产生性质\\物种与身体结构\\身体结构\\身体结构-数量\\额外眼.md"
  },
  "产生性质\\物种与身体结构\\身体结构\\身体结构-数量\\额外阴茎.md": {
    "id": 8,
    "batch_folder": "0",
    "new_name": "8.md",
    "new_path": "0/8.md",
    "abs_source": "works\\产生性质\\物种与身体结构\\身体结构\\身体结构-数量\\额外阴茎.md"
  },
  "产生性质\\物种与身体结构\\身体结构\\身体结构-数量\\额外阴道.md": {
    "id": 13,
    "batch_folder": "0",
    "new_name": "13.md",
    "new_path": "0/13.md",
    "abs_source": "works\\产生性质\\物种与身体结构\\身体结构\\身体结构-数量\\额外阴道.md"
  },
  "产生性质\\行为与表现\\表现\\阿黑颜.md": {
    "id": 15,
    "batch_folder": "0",
    "new_name": "15.md",
    "new_path": "0/15.md",
    "abs_source": "works\\产生性质\\行为与表现\\表现\\阿黑颜.md"
  },
  "产生性质\\行为与表现\\行为\\性行为\\index.md": {
    "id": 25,
    "batch_folder": "0",
    "new_name": "25.md",
    "new_path": "0/25.md",
    "abs_source": "works\\产生性质\\行为与表现\\行为\\性行为\\index.md"
  },
  "产生性质\\行为与表现\\行为\\摄取\\index.md": {
    "id": 5,
    "batch_folder": "0",
    "new_name": "5.md",
    "new_path": "0/5.md",
    "abs_source": "works\\产生性质\\行为与表现\\行为\\摄取\\index.md"
  },
  "产生性质\\行为与表现\\行为\\摄取\\丸吞.md": {
    "id": 18,
    "batch_folder": "0",
    "new_name": "18.md",
    "new_path": "0/18.md",
    "abs_source": "works\\产生性质\\行为与表现\\行为\\摄取\\丸吞.md"
  },
  "产生性质\\行为与表现\\行为\\生育\\肛门分娩.md": {
    "id": 27,
    "batch_folder": "0",
    "new_name": "27.md",
    "new_path": "0/27.md",
    "abs_source": "works\\产生性质\\行为与表现\\行为\\生育\\肛门分娩.md"
  },
  "产生性质\\行为与表现\\行为\\贯穿\\index.md": {
    "id": 19,
    "batch_folder": "0",
    "new_name": "19.md",
    "new_path": "0/19.md",
    "abs_source": "works\\产生性质\\行为与表现\\行为\\贯穿\\index.md"
  },
  "产生性质\\行为与表现\\行为\\贯穿\\穿刺.md": {
    "id": 17,
    "batch_folder": "0",
    "new_name": "17.md",
    "new_path": "0/17.md",
    "abs_source": "works\\产生性质\\行为与表现\\行为\\贯穿\\穿刺.md"
  },
  "产生性质\\行为与表现\\行为\\性行为\\插入介质\\肛交.md": {
    "id": 26,
    "batch_folder": "0",
    "new_name": "26.md",
    "new_path": "0/26.md",
    "abs_source": "works\\产生性质\\行为与表现\\行为\\性行为\\插入介质\\肛交.md"
  },
  "学术性质\\医学\\解剖学\\index.md": {
    "id": 23,
    "batch_folder": "0",
    "new_name": "23.md",
    "new_path": "0/23.md",
    "abs_source": "works\\学术性质\\医学\\解剖学\\index.md"
  },
  "学术性质\\医学\\疾病\\皮肤疾病\\index.md": {
    "id": 22,
    "batch_folder": "0",
    "new_name": "22.md",
    "new_path": "0/22.md",
    "abs_source": "works\\学术性质\\医学\\疾病\\皮肤疾病\\index.md"
  },
  "学术性质\\医学\\疾病\\皮肤疾病\\白化病.md": {
    "id": 16,
    "batch_folder": "0",
    "new_name": "16.md",
    "new_path": "0/16.md",
    "abs_source": "works\\学术性质\\医学\\疾病\\皮肤疾病\\白化病.md"
  },
  "学术性质\\医学\\疾病\\身体结构缺失\\index.md": {
    "id": 21,
    "batch_folder": "0",
    "new_name": "21.md",
    "new_path": "0/21.md",
    "abs_source": "works\\学术性质\\医学\\疾病\\身体结构缺失\\index.md"
  },
  "学术性质\\医学\\疾病\\身体结构缺失\\截肢.md": {
    "id": 20,
    "batch_folder": "0",
    "new_name": "20.md",
    "new_path": "0/20.md",
    "abs_source": "works\\学术性质\\医学\\疾病\\身体结构缺失\\截肢.md"
  },
  "学术性质\\医学\\解剖学\\头颈部\\口.md": {
    "id": 9,
    "batch_folder": "0",
    "new_name": "9.md",
    "new_path": "0/9.md",
    "abs_source": "works\\学术性质\\医学\\解剖学\\头颈部\\口.md"
  },
  "学术性质\\医学\\解剖学\\头颈部\\眼.md": {
    "id": 12,
    "batch_folder": "0",
    "new_name": "12.md",
    "new_path": "0/12.md",
    "abs_source": "works\\学术性质\\医学\\解剖学\\头颈部\\眼.md"
  },
  "学术性质\\医学\\解剖学\\躯干\\消化系统\\肛门.md": {
    "id": 24,
    "batch_folder": "0",
    "new_name": "24.md",
    "new_path": "0/24.md",
    "abs_source": "works\\学术性质\\医学\\解剖学\\躯干\\消化系统\\肛门.md"
  },
  "学术性质\\医学\\解剖学\\躯干\\生殖系统\\阴茎.md": {
    "id": 11,
    "batch_folder": "0",
    "new_name": "11.md",
    "new_path": "0/11.md",
    "abs_source": "works\\学术性质\\医学\\解剖学\\躯干\\生殖系统\\阴茎.md"
  },
  "学术性质\\医学\\解剖学\\躯干\\生殖系统\\阴道.md": {
    "id": 14,
    "batch_folder": "0",
    "new_name": "14.md",
    "new_path": "0/14.md",
    "abs_source": "works\\学术性质\\医学\\解剖学\\躯干\\生殖系统\\阴道.md"
  },
  "普遍性质\\行为\\堕胎.md": {
    "id": 4,
    "batch_folder": "0",
    "new_name": "4.md",
    "new_path": "0/4.md",
    "abs_source": "works\\普遍性质\\行为\\堕胎.md"
  }
}